ec2_utils/__init__.py
ec2_utils/block_devices.py
ec2_utils/cli.py
ec2_utils/ebs.py
ec2_utils/ec2.py
ec2_utils/ecs.py
ec2_utils/elastic_c2_register_complete.py
ec2_utils/instance_info.py
ec2_utils/interface.py
ec2_utils/logs.py
ec2_utils/s3.py
ec2_utils/utils.py
ec2_utils/words.py
ec2_utils/includes/create-shell-archive.sh
ec2_utils/includes/disk-by-drive-letter.ps1
ec2_utils/includes/encrypt-and-mount.sh
ec2_utils/includes/mount-and-format.sh
ec2_utils/includes/ssh-hostkeys-collect.sh
ec2_utils-0.39.dist-info/licenses/LICENSE
ec2_utils-0.39.dist-info/METADATA
ec2_utils-0.39.dist-info/WHEEL
ec2_utils-0.39.dist-info/entry_points.txt
ec2_utils-0.39.dist-info/top_level.txt
ec2_utils-0.39.dist-info/RECORD
