Metadata-Version: 2.4
Name: ec2-utils
Version: 0.39
Summary: Tools for using on an ec2 instance
Home-page: http://github.com/NitorCreations/ec2-utils
Download-URL: https://github.com/NitorCreations/ec2-utils/tarball/0.39
Author: Pasi Niemi
Author-email: pasi@nitor.com
License: Apache 2.0
License-File: LICENSE
Requires-Dist: future
Requires-Dist: threadlocal-aws>=0.10
Requires-Dist: requests
Requires-Dist: termcolor
Requires-Dist: argcomplete
Requires-Dist: python-dateutil
Requires-Dist: retry
Requires-Dist: netifaces2
Requires-Dist: jmespath
Dynamic: author
Dynamic: author-email
Dynamic: download-url
Dynamic: home-page
Dynamic: license
Dynamic: license-file
Dynamic: requires-dist
Dynamic: summary
